AUTHORS
CHANGES
LICENSE
MANIFEST.in
README.rst
setup.py
bin/wkhtmltopdf-heroku
pywkher/__init__.py
pywkher.egg-info/PKG-INFO
pywkher.egg-info/SOURCES.txt
pywkher.egg-info/dependency_links.txt
pywkher.egg-info/not-zip-safe
pywkher.egg-info/requires.txt
pywkher.egg-info/top_level.txt